silver_platter.cpython-313-darwin.so
silver_platter-0.5.48.dist-info/RECORD
silver_platter-0.5.48.dist-info/WHEEL
silver_platter-0.5.48.dist-info/top_level.txt
silver_platter-0.5.48.dist-info/METADATA
silver_platter-0.5.48.dist-info/licenses/LICENSE
silver_platter-0.5.48.dist-info/licenses/AUTHORS
