Metadata-Version: 2.4
Name: silver-platter
Version: 0.5.48
Summary: Large scale VCS change management
Author-email: Jelmer Vernooij <jelmer@jelmer.uk>
License-Expression: GPL-3.0-or-later
Project-URL: Homepage, https://jelmer.uk/code/silver-platter
Project-URL: Bug Tracker, https://github.com/jelmer/silver-platter/issues
Project-URL: Repository, https://github.com/jelmer/silver-platter
Project-URL: GitHub, https://github.com/jelmer/silver-platter
Keywords: git bzr vcs github gitlab launchpad
Classifier: Development Status :: 3 - Alpha
Classifier: Programming Language :: Python :: 3.13
Classifier: Programming Language :: Python :: 3.12
Classifier: Programming Language :: Python :: 3.11
Classifier: Programming Language :: Python :: 3.10
Classifier: Programming Language :: Python :: 3.9
Classifier: Programming Language :: Python :: Implementation :: CPython
Classifier: Programming Language :: Python :: Implementation :: PyPy
Classifier: Operating System :: POSIX
Classifier: Topic :: Software Development :: Version Control
Requires-Python: >=3.9
License-File: LICENSE
License-File: AUTHORS
Requires-Dist: breezy>=3.3.3
Requires-Dist: dulwich>=0.20.23
Requires-Dist: jinja2
Requires-Dist: pyyaml
Requires-Dist: ruamel.yaml
Provides-Extra: debian
Requires-Dist: debmutate>=0.3; extra == "debian"
Requires-Dist: python_debian>=0.1.48; extra == "debian"
Requires-Dist: brz-debian; extra == "debian"
Provides-Extra: launchpad
Requires-Dist: launchpadlib; extra == "launchpad"
Provides-Extra: detect-gbp-dch
Requires-Dist: lintian-brush; extra == "detect-gbp-dch"
Provides-Extra: testing
Requires-Dist: testtools; extra == "testing"
Requires-Dist: debmutate>=0.3; extra == "testing"
Requires-Dist: python-debian; extra == "testing"
Requires-Dist: brz-debian; extra == "testing"
Provides-Extra: dev
Requires-Dist: ruff==0.12.5; extra == "dev"
Dynamic: license-file
